netsalt/__init__.py
netsalt/algorithm.py
netsalt/io.py
netsalt/modes.py
netsalt/physics.py
netsalt/plotting.py
netsalt/pump.py
netsalt/quantum_graph.py
netsalt/utils.py
netsalt/tasks/__init__.py
netsalt/tasks/analysis.py
netsalt/tasks/config.py
netsalt/tasks/lasing.py
netsalt/tasks/netsalt_task.py
netsalt/tasks/passive.py
netsalt/tasks/pump.py
netsalt/tasks/workflow.py
netsalt-0.2.0.dist-info/LICENSE
netsalt-0.2.0.dist-info/METADATA
netsalt-0.2.0.dist-info/WHEEL
netsalt-0.2.0.dist-info/top_level.txt
netsalt-0.2.0.dist-info/RECORD
